envwizard/__init__.py
envwizard/core.py
envwizard/logger.py
envwizard/venv.py
envwizard/cli/__init__.py
envwizard/cli/main.py
envwizard/detectors/__init__.py
envwizard/detectors/base.py
envwizard/detectors/dependency.py
envwizard/detectors/framework.py
envwizard/generators/__init__.py
envwizard/generators/dotenv.py
envwizard-0.2.1.dist-info/METADATA
envwizard-0.2.1.dist-info/WHEEL
envwizard-0.2.1.dist-info/entry_points.txt
envwizard-0.2.1.dist-info/licenses/LICENSE
envwizard-0.2.1.dist-info/RECORD
