Metadata-Version: 2.4
Name: envwizard
Version: 0.2.1
Summary: Smart environment setup tool - One command to create virtual envs, install deps, and configure .env intelligently
Project-URL: Homepage, https://github.com/0xV8/envwizard
Project-URL: Documentation, https://github.com/0xV8/envwizard#readme
Project-URL: Repository, https://github.com/0xV8/envwizard
Project-URL: Bug Tracker, https://github.com/0xV8/envwizard/issues
Author-email: Vipin <vipin@example.com>
License: MIT
License-File: LICENSE
Keywords: automation,development,dotenv,environment,productivity,setup,virtualenv
Classifier: Development Status :: 4 - Beta
Classifier: Intended Audience :: Developers
Classifier: License :: OSI Approved :: MIT License
Classifier: Operating System :: OS Independent
Classifier: Programming Language :: Python :: 3
Classifier: Programming Language :: Python :: 3.9
Classifier: Programming Language :: Python :: 3.10
Classifier: Programming Language :: Python :: 3.11
Classifier: Programming Language :: Python :: 3.12
Classifier: Topic :: Software Development :: Libraries :: Python Modules
Classifier: Topic :: Utilities
Requires-Python: >=3.9
Requires-Dist: click>=8.0.0
Requires-Dist: python-dotenv>=1.0.0
Requires-Dist: pyyaml>=6.0
Requires-Dist: rich>=13.0.0
Provides-Extra: dev
Requires-Dist: black>=23.0.0; extra == 'dev'
Requires-Dist: mypy>=1.0.0; extra == 'dev'
Requires-Dist: pre-commit>=3.0.0; extra == 'dev'
Requires-Dist: pytest-cov>=4.0.0; extra == 'dev'
Requires-Dist: pytest>=7.0.0; extra == 'dev'
Requires-Dist: ruff>=0.1.0; extra == 'dev'
